{
  "aliexpressdz_coupons": {
    "id": "1836978656",
    "title": "(AliExpress offers)",
    "accessHash": "2120885676793801020"
  },
  "vrscoupons": {
    "id": "1361915769",
    "title": "~VRS~COUPONS ®",
    "accessHash": "6161785463922151842"
  },
  "kscoupons": {
    "id": "1408385608",
    "title": "🎉عروض علي إكسبريس🎉",
    "accessHash": "-6984266521576545712"
  },
  "dzmac": {
    "id": "1528697188",
    "title": "🔴🔴 حسان كوبون 🔴🔴",
    "accessHash": "-5354961513753978092"
  },
  "bestpromotion10": {
    "id": "1767602652",
    "title": "🥇BEST PROMO🥇",
    "accessHash": "8312652493355392663"
  },
  "x88123": {
    "id": "1166253339",
    "title": "🛍 aliexpress | تسوق مع فراس",
    "accessHash": "-3918189829820712054"
  },
  "fantastic_shope": {
    "id": "2074564359",
    "title": "🛍 خصومات وعروض علي اكسبريس",
    "accessHash": "3810121131196459193"
  },
  "boukhatemq": {
    "id": "3190809365",
    "title": "Ahmed",
    "accessHash": "-8221686908741265903"
  },
  "ahmedcoupons": {
    "id": "1713711695",
    "title": "Ahmed coupons",
    "accessHash": "-3951048960065472651"
  },
  "alieexdeals": {
    "id": "1610861300",
    "title": "Alie Ex Deals افضل العروض و الكوبونات",
    "accessHash": "4905847096014039673"
  },
  "aliexpress_algeria_coupon": {
    "id": "1885553695",
    "title": "Aliexpress Algeria coupon (Cici Coupons)",
    "accessHash": "282508606375783962"
  },
  "aliexpress_dzairr": {
    "id": "1842832028",
    "title": "Aliexpress Algerie تخفيضات",
    "accessHash": "7381440348852653762"
  },
  "couponcn": {
    "id": "1272198314",
    "title": "Aliexpress Banggood Coupons",
    "accessHash": "-6173276872046650053"
  },
  "aliexpressbroficial": {
    "id": "1473618074",
    "title": "AliExpress Brasil - OFICIAL",
    "accessHash": "5232046790832809137"
  },
  "couponsglobal": {
    "id": "1201414920",
    "title": "AliExpress Coupons & Getbest",
    "accessHash": "6619618674628364207"
  },
  "aliexpcodespromos": {
    "id": "1206524589",
    "title": "Aliexpress Deals | Coupons | Codes Promos",
    "accessHash": "3657279565231655799"
  },
  "aliexpresddiscounts": {
    "id": "1310406538",
    "title": "Aliexpress discounts",
    "accessHash": "4268692309071252306"
  },
  "aliexpressdz2026": {
    "id": "3328881458",
    "title": "Aliexpress DZ",
    "accessHash": "4469641375670017201"
  },
  "aliexpress_offers_dz": {
    "id": "1713441028",
    "title": "AliExpress offers in Algeria",
    "accessHash": "-1974323451124995260"
  },
  "aliexpress_arabs": {
    "id": "1644529752",
    "title": "ALIEXPRESS PROMO تخفيضات علي إكسبريس",
    "accessHash": "4790317881582500734"
  },
  "m3djisyvtswwmwrk": {
    "id": "1812451766",
    "title": "Aliexpress with Amine",
    "accessHash": "-469462585284725716"
  },
  "aliexpress_offer1": {
    "id": "1634727300",
    "title": "AliExpress_Offer 🛒🔥",
    "accessHash": "6407935639665298567"
  },
  "alicouponsbonus": {
    "id": "1497128732",
    "title": "AliSuper Coupons ™",
    "accessHash": "3926659660367291911"
  },
  "amazonstoredz": {
    "id": "3723903170",
    "title": "Amazon",
    "accessHash": "5504799742148264216"
  },
  "aminebestseller": {
    "id": "1688885533",
    "title": "Amine Coupons 🎁",
    "accessHash": "-8144760070436405375"
  },
  "aniscoupons": {
    "id": "1163206790",
    "title": "ANIS Coupons🛍🎁🎫",
    "accessHash": "-7688153686678540390"
  },
  "badrexpress2": {
    "id": "1389222154",
    "title": "Badr express 2",
    "accessHash": "-7532025843527773734"
  },
  "bestcoupons3": {
    "id": "1479149671",
    "title": "Best coupons 🔥🔥",
    "accessHash": "5242268822229035065"
  },
  "bestdeelz": {
    "id": "1464275574",
    "title": "Best Deals",
    "accessHash": "-2139794518503404359"
  },
  "bestdealzdz": {
    "id": "1977607613",
    "title": "Best Dealz Aliexpress 🇩🇿",
    "accessHash": "-6928541905823543939"
  },
  "dzbestdeal": {
    "id": "1813093015",
    "title": "Best offers 🔥🔥",
    "accessHash": "-4745510845067015714"
  },
  "bitgetwalletlite_announcement": {
    "id": "2296878359",
    "title": "Bitget Wallet Lite News",
    "accessHash": "-2093053977299094462"
  },
  "blockbitsapp": {
    "id": "2432381215",
    "title": "BlockBits",
    "accessHash": "6803424006494103472"
  },
  "bmcoupons": {
    "id": "1618115041",
    "title": "ʙᴍ ᴄᴏᴜᴘᴏɴꜱ ™",
    "accessHash": "-1673413494023041496"
  },
  "capybara_meme_official": {
    "id": "2358621468",
    "title": "Capybara Official Community",
    "accessHash": "6062259330687193995"
  },
  "aliexpress_dzd": {
    "id": "1254982058",
    "title": "c͓̽o͓̽u͓̽p͓̽o͓̽n͓̽s͓̽",
    "accessHash": "341332843483150547"
  },
  "cpndcc": {
    "id": "1469662610",
    "title": "Coupons ©™",
    "accessHash": "7588508294736652408"
  },
  "couponscodes_dz": {
    "id": "1263926460",
    "title": "COUPONS CODES DZ 🇩🇿",
    "accessHash": "-7604295978099285874"
  },
  "couponsfordz": {
    "id": "1666141662",
    "title": "Coupons For Algeria™",
    "accessHash": "-7682309657132699702"
  },
  "-1001310711172": {
    "id": "1310711172",
    "title": "Coupons94™ 🛒| Deals Online",
    "accessHash": "7935870751548197482"
  },
  "cr_halal": {
    "id": "1426595606",
    "title": "CRYPTOHALAL كريبتو حلال",
    "accessHash": "5470747961990812855"
  },
  "deals_couponss": {
    "id": "1341335354",
    "title": "Deals Coupons™",
    "accessHash": "608224092669636141"
  },
  "discountinadz": {
    "id": "1432761774",
    "title": "Discountina Dz",
    "accessHash": "4198625229137390240"
  },
  "dzmaxdeals": {
    "id": "1872203541",
    "title": "DZ MAX DEALS",
    "accessHash": "-4962551548607982327"
  },
  "dzcouponcoins": {
    "id": "2173599778",
    "title": "DZCOUPONS ™ 🇩🇿",
    "accessHash": "6942636233103746072"
  },
  "dzcouponz": {
    "id": "1636303557",
    "title": "DzCouponZ",
    "accessHash": "7206985323712378054"
  },
  "dzsooh": {
    "id": "1217180882",
    "title": "DzShoo",
    "accessHash": "4709015533846202170"
  },
  "o_trade_dz": {
    "id": "1097055886",
    "title": "DZSHOP COUPON",
    "accessHash": "4453386057170764795"
  },
  "expertoffers": {
    "id": "1442759150",
    "title": "Expert Aliexpress",
    "accessHash": "-9139130384495382204"
  },
  "gbarabia": {
    "id": "1445526907",
    "title": "Express Coupons",
    "accessHash": "-5647432357875606791"
  },
  "bestoffers5": {
    "id": "1559817110",
    "title": "Firas coupons 🇩🇿🇩🇿",
    "accessHash": "-204138293507741936"
  },
  "froxendeals": {
    "id": "1491550126",
    "title": "FROXEN COUPONS™",
    "accessHash": "4510725071785361979"
  },
  "getbestcoupons": {
    "id": "1318023156",
    "title": "GetBest Coupons Ⓐ",
    "accessHash": "-6638295684045603229"
  },
  "getitcoupon": {
    "id": "1802688098",
    "title": "Getitcoupon",
    "accessHash": "2963503328439238200"
  },
  "-1001029902375": {
    "id": "1029902375",
    "title": "Graph Messenger",
    "accessHash": "-611499834498329068"
  },
  "hadjicoupon": {
    "id": "1538819758",
    "title": "HADJI COUPONS AliExpress",
    "accessHash": "-4677935824047330061"
  },
  "hasritechstore": {
    "id": "1647167969",
    "title": "Hasri Tech Store",
    "accessHash": "8078736201901283059"
  },
  "hightaskofficial": {
    "id": "1451762016",
    "title": "High Task Official Channel",
    "accessHash": "-4624343874191214099"
  },
  "hocine_coupons": {
    "id": "1345840527",
    "title": "Hocine Coupons🛍",
    "accessHash": "4224293725907915116"
  },
  "hunterdealdz": {
    "id": "3687941257",
    "title": "Hunter deals dz",
    "accessHash": "-3563004251825043820"
  },
  "aliexpress_shopping17": {
    "id": "1654389621",
    "title": "Khaled Coupons",
    "accessHash": "-846293395486141628"
  },
  "l7oushopping": {
    "id": "2052203800",
    "title": "L7ou.Express",
    "accessHash": "-7043886762416545398"
  },
  "lkrenaliexpress": {
    "id": "1885675994",
    "title": "LKRNE ALIEXPRESS",
    "accessHash": "-4293271021633052011"
  },
  "promotiondz": {
    "id": "1755854394",
    "title": "NASRO COUPONS",
    "accessHash": "-901207375519677789"
  },
  "-1001611381853": {
    "id": "1611381853",
    "title": "Neko Coupons DZ",
    "accessHash": "5826407050270433359"
  },
  "faysal_shoping": {
    "id": "2014430999",
    "title": "Products al!express amazing",
    "accessHash": "2311704539248061761"
  },
  "pulsesocialannouncements": {
    "id": "2055564160",
    "title": "Pulse Announcements",
    "accessHash": "-1473156077659950883"
  },
  "rabahcopons": {
    "id": "1739642672",
    "title": "Rabah Coupons",
    "accessHash": "8595969365470289287"
  },
  "rbdeals1": {
    "id": "1892018147",
    "title": "RB DEALS",
    "accessHash": "1085131539652193115"
  },
  "ringocoupon": {
    "id": "1481470337",
    "title": "Ringo Shop (Deals, ✂️ Coupons ) 🇩🇿",
    "accessHash": "-7612826328159518079"
  },
  "rtdealss": {
    "id": "1246403256",
    "title": "RT DEALS™",
    "accessHash": "3196562712789820268"
  },
  "-1001851623096": {
    "id": "1851623096",
    "title": "Sal Coupons",
    "accessHash": "-4282468692665716303"
  },
  "superldels": {
    "id": "1395147314",
    "title": "️SALAH Coupons 💸💳📱",
    "accessHash": "-7623418769330821773"
  },
  "tttttt6": {
    "id": "2200317955",
    "title": "Save Restricted Ar",
    "accessHash": "-5223651788006161648"
  },
  "nosachats": {
    "id": "1198476336",
    "title": "Savvy Deals Zone",
    "accessHash": "4170862613378893592"
  },
  "shopedz": {
    "id": "1324904975",
    "title": "ShopeDZ",
    "accessHash": "-1321825521948296150"
  },
  "sl8_news": {
    "id": "1557805161",
    "title": "Sl8 Community News 🚀",
    "accessHash": "-6135951913038994630"
  },
  "smartcoupon": {
    "id": "1642765021",
    "title": "Smart Coupons ™",
    "accessHash": "574825333969996917"
  },
  "smart_store06": {
    "id": "1654390284",
    "title": "Smart Store",
    "accessHash": "55920932005989055"
  },
  "solo_coupon": {
    "id": "2169874785",
    "title": "Solo Coupon",
    "accessHash": "4915246511378389168"
  },
  "soummam": {
    "id": "1244033554",
    "title": "Soummam Coupons",
    "accessHash": "-4945130120806945605"
  },
  "alioffers17": {
    "id": "1577086221",
    "title": "TAHA COUPONS ™",
    "accessHash": "-122088003267865302"
  },
  "x555xx173": {
    "id": "1841698827",
    "title": "TECH DEALS SHOP",
    "accessHash": "-3607189675564608073"
  },
  "ali_dz_213": {
    "id": "1520008194",
    "title": "TOP ALIEXPRESS 🇩🇿🇲🇦",
    "accessHash": "-1168555165188321492"
  },
  "ziamoamed": {
    "id": "1654749304",
    "title": "Top Deals DZ",
    "accessHash": "-5688629982043060582"
  },
  "tredingsoon": {
    "id": "1818344549",
    "title": "Trading_wk",
    "accessHash": "-9176553711255786008"
  },
  "cefoor": {
    "id": "1399490491",
    "title": "Video",
    "accessHash": "-2921536212447155345"
  },
  "yacine_coupon": {
    "id": "1533778418",
    "title": "Yacine_coupon",
    "accessHash": "2395827531033462152"
  },
  "dycoupons": {
    "id": "1707928737",
    "title": "YOUS COUPONS ™ 🥇",
    "accessHash": "8530815496062316959"
  },
  "zedstoreonline": {
    "id": "1701453842",
    "title": "Zed Store Online",
    "accessHash": "7804021079319086581"
  },
  "abbasyousifjasim": {
    "id": "1513745765",
    "title": "آراء - opinions",
    "accessHash": "932925903970609181"
  },
  "aliexpress_dz_promo": {
    "id": "1570180016",
    "title": "أفضل عروض علي إكسبرس 😍🔥 شراء من الأنترنت 🛒🛍",
    "accessHash": "5488198040929047009"
  },
  "aliexpressbillel": {
    "id": "1616111139",
    "title": "التسوق من الانترنت - Aliexpress",
    "accessHash": "-7585697779965966031"
  },
  "alialiexpressoffers": {
    "id": "1236797597",
    "title": "تخفيضات Aliexpress",
    "accessHash": "1475444813600120293"
  },
  "aliexcouponsdz": {
    "id": "1435618812",
    "title": "تخفيضات aliexpress 🔥",
    "accessHash": "8214737484989015336"
  },
  "aliexdealsandcoupons": {
    "id": "1189615286",
    "title": "تخفيضات المتاجر الصينية",
    "accessHash": "9049196514477360435"
  },
  "hamizataliexpress": {
    "id": "1229281800",
    "title": "تخفيضات علي اكسبريس 🔥",
    "accessHash": "8559588211735387576"
  },
  "s8y8s": {
    "id": "1619301179",
    "title": "ذكرى",
    "accessHash": "8681204363171164586"
  },
  "cefoors": {
    "id": "1318527838",
    "title": "سوبر ماركت متكاتفون",
    "accessHash": "-3319316857729867590"
  },
  "monayaatfrid": {
    "id": "1771325337",
    "title": "عبدالباسط فريد",
    "accessHash": "-2286113175216212525"
  },
  "fdzaliex": {
    "id": "2045091165",
    "title": "علي إكسبريس الجزائر 🇩🇿",
    "accessHash": "-1841765924226937917"
  },
  "shope077": {
    "id": "1853446518",
    "title": "عمي شينوي (TEMU /ALIEXPRESS)",
    "accessHash": "-6767515492833278684"
  },
  "supercouponsdeals": {
    "id": "1710450941",
    "title": "قناة خاصة بعروض aliexpress",
    "accessHash": "8333329985340143082"
  },
  "-1001601065591": {
    "id": "1601065591",
    "title": "كوبونات Aliexpress",
    "accessHash": "974388095519932946"
  },
  "za_sc": {
    "id": "1983129567",
    "title": "متجر بيع شراء حسابات ببجي",
    "accessHash": "2539583097672182413"
  },
  "botsefoor": {
    "id": "1923604791",
    "title": "متكاتفون",
    "accessHash": "6656697526372262836"
  },
  "aliexpressgroupbay6": {
    "id": "1624663351",
    "title": "✨تبادل الروابط ✨ لموقع 🟡✨Aliexpress",
    "accessHash": "4563155614700551392"
  },
  "aliexpresscoupondzmac": {
    "id": "1528222394",
    "title": "🎁 تخفيضات المواقع الصينية 🎁",
    "accessHash": "3690003609445971163"
  },
  "ahmedcoupons21": {
    "id": "1781797719",
    "title": "Ahmed-Coupons 🔥",
    "accessHash": "-94763533507874793"
  },
  "algeriealiexpress": {
    "id": "1930811137",
    "title": "Aliexpress Algérien",
    "accessHash": "-7173373101125573988"
  },
  "-1001781987841": {
    "id": "1781987841",
    "title": "ALIEXPRESS عروض علي اكسبريس🥇 Chat",
    "accessHash": "2831007816249864565"
  },
  "segalamoja": {
    "id": "1783058704",
    "title": "Coupons mouja🛒🎊",
    "accessHash": "2266262400570715221"
  },
  "-1001625499901": {
    "id": "1625499901",
    "title": "DZ-استثمر عقلك",
    "accessHash": "1475461402064182812"
  },
  "-1001414213012": {
    "id": "1414213012",
    "title": "Dzshoo",
    "accessHash": "8860482294670265238"
  },
  "groupebuy": {
    "id": "1767878858",
    "title": "Esysoug",
    "accessHash": "-3973395776452158198"
  },
  "gotyourdeal": {
    "id": "1760391582",
    "title": "Got Your Deal",
    "accessHash": "-9002933604283060225"
  },
  "lodycoupons": {
    "id": "1646790519",
    "title": "LODY DEALS CHAT 🏷",
    "accessHash": "-7904526690682805815"
  },
  "megasold": {
    "id": "1591629214",
    "title": "Mega Solde",
    "accessHash": "171392763031476788"
  },
  "aliexpress_dealss": {
    "id": "1740520691",
    "title": "MS Deals",
    "accessHash": "-7125169299171485971"
  },
  "mouhsin4991": {
    "id": "1578289948",
    "title": "MT COUPONNN",
    "accessHash": "6490049183969476632"
  },
  "promo_aliexpress_26": {
    "id": "1988009028",
    "title": "Promo_Aliexpress",
    "accessHash": "-2187852568642961223"
  },
  "sl8_community": {
    "id": "1422519619",
    "title": "Sl8 Community (SSLX)",
    "accessHash": "86304157591849091"
  },
  "tech_with_akram": {
    "id": "1586139643",
    "title": "tech_with_akram offers",
    "accessHash": "3693156764511160544"
  },
  "achatgroupee": {
    "id": "1659724750",
    "title": "الشراء الجماعي | Achat Groupé",
    "accessHash": "4480863225863453055"
  },
  "alicoupones": {
    "id": "1613152294",
    "title": "تخفيضات كبونات",
    "accessHash": "4629728695479847949"
  },
  "supercouponsteam": {
    "id": "1658005592",
    "title": "عروض الشراء الجماعي",
    "accessHash": "-7621385020595658797"
  },
  "shopping_now_ali_express": {
    "id": "1284870493",
    "title": "عروض علي اكسبريس aliexpress",
    "accessHash": "8606993426493055683"
  },
  "azizbnkf": {
    "id": "1797947132",
    "title": "عروض وتخفيضات موقع Alixpress",
    "accessHash": "-7713782750739576414"
  },
  "dzfix": {
    "id": "1372270225",
    "title": "مساعدة الشراء الجماعي Aliexpress",
    "accessHash": "-6121051414244544088"
  }
}